{"composables_use-scroll-lock.md":"18a500c5","components_phone.md":"13e51f9b","components_textarea.md":"6c7acd1d","components_input-masked.md":"dda82f89","components_input.md":"32b17c8b","composables_use-highlighted-text.md":"c9da0327","composables_use-submit-form.md":"fe45a7c2","components_password.md":"ca524b95","composables_use-fetch-auth.md":"924f5852","api_sitemap.md":"02df2ddc","composables_use-phone-formatter.md":"3712dd31","installation.md":"3fa03dbb","composables_use-scroll-slider.md":"9a6c7500","index.md":"150c5ce4","composables_use-pagination.md":"eb545b5d","composables_use-price-formatter.md":"4243387f","composables_use-sanitize.md":"a6310e5b","components_map-widget.md":"d949fa95"}
